dbutils_phornee/__init__.py
dbutils_phornee/db_conn.py
dbutils_phornee/influxdb_conn.py
dbutils_phornee/mariadb_conn.py
dbutils_phornee/mongodb_conn.py
dbutils_phornee-0.1.3.dist-info/METADATA
dbutils_phornee-0.1.3.dist-info/WHEEL
dbutils_phornee-0.1.3.dist-info/top_level.txt
dbutils_phornee-0.1.3.dist-info/RECORD
